data_quality/__init__.py
data_quality/accuracy_analyzer.py
data_quality/consistency_analyzer.py
data_quality/data_type_analyzer.py
data_quality/missing_values_analyzer.py
data_quality/outlier_analyzer.py
data_quality/timeliness_analyzer.py
data_quality/uniqueness_analyzer.py
data_quality/validity_analyzer.py
data_quality_views/__init__.py
data_quality_views/accuracy_analysis.py
data_quality_views/consistency_analysis.py
data_quality_views/data_type_analysis.py
data_quality_views/missing_values_analysis.py
data_quality_views/outlier_analysis.py
data_quality_views/timeliness_analysis.py
data_quality_views/uniqueness_analysis.py
data_quality_views/validity_analysis.py
explore_df/__init__.py
explore_df/analyzer.py
explore_df/main.py
explore_df/plotter.py
explore_df/.streamlit/config.toml
explore_df/streamlit-pages/0_Dataset_Overview_and_Insights.py
explore_df/streamlit-pages/10_Accepted_Suggestions.py
explore_df/streamlit-pages/1_Univariate_Analysis.py
explore_df/streamlit-pages/2_Bivariate_Analysis.py
explore_df/streamlit-pages/3_Time_Series.py
explore_df/streamlit-pages/4_Categorical_Analysis.py
explore_df/streamlit-pages/5_Feature_Relationships.py
explore_df/streamlit-pages/6_Data_Quality.py
explore_df/streamlit-pages/7_Charts.py
explore_df/streamlit-pages/8_Data_View.py
explore_df/streamlit-pages/8_Text_Analysis.py
explore_df/streamlit-pages/9_Automated_Insights.py
explore_df/streamlit-pages/_Home.py
explore_df-0.1.13.dist-info/licenses/LICENSE
explore_df-0.1.13.dist-info/METADATA
explore_df-0.1.13.dist-info/WHEEL
explore_df-0.1.13.dist-info/top_level.txt
explore_df-0.1.13.dist-info/RECORD
