Metadata-Version: 2.4
Name: explore-df
Version: 0.1.13
Summary: A one-line interactive EDA tool using Streamlit
Author: Mandla Sibanda
Author-email: Mandla Sibanda <mandla.sibanda@gmail.com>
Project-URL: Homepage, https://github.com/MandlaSibanda196/explore-df
Project-URL: Bug Tracker, https://github.com/MandlaSibanda196/explore-df/issues
Classifier: Programming Language :: Python :: 3
Classifier: License :: OSI Approved :: MIT License
Classifier: Operating System :: OS Independent
Requires-Python: >=3.9
License-File: LICENSE
Requires-Dist: streamlit>=1.44.0
Requires-Dist: pandas>=2.0.0
Requires-Dist: plotly>=5.14.0
Requires-Dist: numpy>=1.24.0
Requires-Dist: scipy>=1.10.0
Requires-Dist: statsmodels>=0.14.0
Requires-Dist: scikit-learn>=1.3.0
Requires-Dist: ruptures>=1.1.7
Requires-Dist: wordcloud>=1.9.2
Requires-Dist: requests>=2.31.0
Requires-Dist: matplotlib>=3.7.0
Requires-Dist: plotly-express>=0.4.0
Dynamic: author
Dynamic: license-file
Dynamic: requires-python
